dynamic_tables/__init__.py
dynamic_tables/dynamic_tables.py
dynamic_tables-0.2.0.dist-info/LICENSE
dynamic_tables-0.2.0.dist-info/METADATA
dynamic_tables-0.2.0.dist-info/WHEEL
dynamic_tables-0.2.0.dist-info/top_level.txt
dynamic_tables-0.2.0.dist-info/RECORD
