Metadata-Version: 2.1
Name: dynamic-tables
Version: 0.2.0
Summary: A dynamic table creation and management library for PostgreSQL
Home-page: https://github.com/scottrodeo/dynamic-tables-python
Author: Scott Rodeo
Author-email: signcactus@gmail.com
License: UNKNOWN
Platform: UNKNOWN
Classifier: Programming Language :: Python :: 3
Classifier: License :: OSI Approved :: MIT License
Classifier: Operating System :: OS Independent
Requires-Python: >=3.6
Requires-Dist: psycopg2
